wxbs_benchmark/__init__.py
wxbs_benchmark/_modidx.py
wxbs_benchmark/_nbdev.py
wxbs_benchmark/dataset.py
wxbs_benchmark/evaluation.py
wxbs_benchmark/metrics.py
wxbs_benchmark-0.0.4.dist-info/LICENSE
wxbs_benchmark-0.0.4.dist-info/METADATA
wxbs_benchmark-0.0.4.dist-info/WHEEL
wxbs_benchmark-0.0.4.dist-info/top_level.txt
wxbs_benchmark-0.0.4.dist-info/RECORD
