Metadata-Version: 2.1
Name: wxbs-benchmark
Version: 0.0.4
Summary: Code for benchmarking image matchers on WxBS dataset
Home-page: https://github.com/ducha-aiki/wxbs_benchmark/tree/master/
Author: Dmytro Mishkin
Author-email: ducha.aiki@gmail.com
License: Apache Software License 2.0
Keywords: WxBS,image matching,benchmark,image correspondences
Classifier: Development Status :: 3 - Alpha
Classifier: Intended Audience :: Developers
Classifier: Natural Language :: English
Classifier: Programming Language :: Python :: 3.6
Classifier: Programming Language :: Python :: 3.7
Classifier: Programming Language :: Python :: 3.8
Classifier: License :: OSI Approved :: Apache Software License
Requires-Python: >=3.6
License-File: LICENSE
Requires-Dist: pip
Requires-Dist: packaging
Requires-Dist: kornia
Requires-Dist: torch
Requires-Dist: numpy
Requires-Dist: matplotlib
Requires-Dist: opencv-python
Requires-Dist: Pillow
Requires-Dist: torchvision
Provides-Extra: dev
